ddr_analysis_tools/__init__.py
ddr_analysis_tools/ddr_FFT.py
ddr_analysis_tools/ddr_POD.py
ddr_analysis_tools/ddr_PSD_welch.py
ddr_analysis_tools/ddr_Recurrance_analysis.py
ddr_analysis_tools/ddr_SPOD.py
ddr_analysis_tools/utils.py
ddr_analysis_tools/version.py
ddr_analysis_tools/pyspod_local/__init__.py
ddr_analysis_tools/pyspod_local/emulation/__init__.py
ddr_analysis_tools/pyspod_local/emulation/base.py
ddr_analysis_tools/pyspod_local/emulation/neural_nets.py
ddr_analysis_tools/pyspod_local/pod/__init__.py
ddr_analysis_tools/pyspod_local/pod/base.py
ddr_analysis_tools/pyspod_local/pod/standard.py
ddr_analysis_tools/pyspod_local/pod/utils.py
ddr_analysis_tools/pyspod_local/spod/__init__.py
ddr_analysis_tools/pyspod_local/spod/base.py
ddr_analysis_tools/pyspod_local/spod/standard.py
ddr_analysis_tools/pyspod_local/spod/streaming.py
ddr_analysis_tools/pyspod_local/spod/utils.py
ddr_analysis_tools/pyspod_local/utils/__init__.py
ddr_analysis_tools/pyspod_local/utils/errors.py
ddr_analysis_tools/pyspod_local/utils/io.py
ddr_analysis_tools/pyspod_local/utils/parallel.py
ddr_analysis_tools/pyspod_local/utils/postproc.py
ddr_analysis_tools/pyspod_local/utils/weights.py
ddr_analysis_tools-0.0.14.dist-info/LICENSE.txt
ddr_analysis_tools-0.0.14.dist-info/METADATA
ddr_analysis_tools-0.0.14.dist-info/WHEEL
ddr_analysis_tools-0.0.14.dist-info/top_level.txt
ddr_analysis_tools-0.0.14.dist-info/RECORD
