Metadata-Version: 2.1
Name: ddr_analysis_tools
Version: 0.0.14
Summary: Package for data analysis tools
Home-page: https://github.com/dev-ddr/ddr_analysis_tools
Author: Darshan Rathod
Author-email: darshan.rathod1994@gmail.com
Keywords: ddr,time series data analysis,data analysis,POD,SPOD,FFT,ddr_FFT,ddr_SPOD,ddr_PODddr_analysis_tools
Classifier: Development Status :: 2 - Pre-Alpha
Classifier: Intended Audience :: Education
Classifier: Intended Audience :: Science/Research
Classifier: Natural Language :: English
Classifier: License :: OSI Approved :: MIT License
Classifier: Topic :: Education
Classifier: Topic :: Scientific/Engineering
Classifier: Topic :: Scientific/Engineering :: Physics
Classifier: Programming Language :: Python :: 3.10
Requires-Python: >=3.10, <4
License-File: LICENSE.txt
Requires-Dist: numpy
Requires-Dist: matplotlib
Requires-Dist: psutil
Requires-Dist: tqdm
Requires-Dist: scipy
Requires-Dist: h5py
Requires-Dist: netcdf4
Requires-Dist: xarray
Requires-Dist: pyyaml
